{"event_id": "EFBO992369", "url": "https://push.api.bbci.co.uk/data/bbc-morph-sport-football-team-lineups-data/event/EFBO992369/version/1.0.8", "data": {"teams": {"homeTeam": {"name": "Macclesfield Town", "nameAbbreviation": "Macclesfield", "players": [{"meta": {"lineFormationPosition": "1", "playerKey": "PO192182", "positionRegular": "goalkeeper", "status": "starter", "uniformNumber": "1"}, "name": {"full": "Kieran O'Hara", "abbreviation": "O'Hara"}, "bookings": [], "substitutions": []}, {"meta": {"lineFormationPosition": "2", "playerKey": "PO167869", "positionRegular": "defender", "status": "starter", "uniformNumber": "19"}, "name": {"full": "James Pearson", "abbreviation": "Pearson"}, "bookings": [], "substitutions": [{"type": "substitution", "timeElapsed": 45, "addedTime": 0, "reason": "Tactical", "replacedBy": {"meta": {"lineFormationPosition": "0", "playerKey": "PO231805", "positionRegular": "defender", "status": "bench", "uniformNumber": "14"}, "name": {"abbreviation": "Welch-Hayes", "first": "Miles", "full": "Miles Welch-Hayes", "last": "Welch-Hayes"}, "stats": {"dateCoverageType": "event", "dateCoverageValue": "EFBO992369", "teamCoverage": "single-team", "timePlayedTotal": "45"}, "bookings": [], "substitutions": []}, "positionOfReplacement": "defender"}]}, {"meta": {"lineFormationPosition": "5", "playerKey": "PO192880", "positionRegular": "defender", "status": "starter", "uniformNumber": "5"}, "name": {"full": "Fiacre Kelleher", "abbreviation": "Kelleher"}, "bookings": [], "substitutions": []}, {"meta": {"lineFormationPosition": "6", "playerKey": "PO74950", "positionRegular": "defender", "status": "starter", "uniformNumber": "6"}, "name": {"full": "Jamie Grimes", "abbreviation": "Grimes"}, "bookings": [{"type": "yellow-card", "timeElapsed": 27, "addedTime": 0}], "substitutions": []}, {"meta": {"lineFormationPosition": "3", "playerKey": "PO168412", "positionRegular": "defender", "status": "starter", "uniformNumber": "3"}, "name": {"full": "David Fitzpatrick", "abbreviation": "Fitzpatrick"}, "bookings": [], "substitutions": []}, {"meta": {"lineFormationPosition": "8", "playerKey": "PO19347", "positionRegular": "midfielder", "status": "starter", "uniformNumber": "24"}, "name": {"full": "Michael Rose", "abbreviation": "Rose"}, "bookings": [], "substitutions": []}, {"meta": {"lineFormationPosition": "4", "playerKey": "PO202721", "positionRegular": "midfielder", "status": "starter", "uniformNumber": "18"}, "name": {"full": "Callum Maycock", "abbreviation": "Maycock"}, "bookings": [], "substitutions": []}, {"meta": {"lineFormationPosition": "7", "playerKey": "PO96747", "positionRegular": "midfielder", "status": "starter", "uniformNumber": "8"}, "name": {"full": "Tyrone Marsh", "abbreviation": "Marsh"}, "bookings": [], "substitutions": []}, {"meta": {"lineFormationPosition": "10", "playerKey": "PO157810", "positionRegular": "midfielder", "status": "starter", "uniformNumber": "22"}, "name": {"full": "Koby Arthur", "abbreviation": "Arthur"}, "bookings": [], "substitutions": [{"type": "substitution", "timeElapsed": 86, "addedTime": 0, "reason": "Tactical", "replacedBy": {"meta": {"lineFormationPosition": "0", "playerKey": "PO432161", "positionRegular": "midfielder", "status": "bench", "uniformNumber": "16"}, "name": {"abbreviation": "Napa", "first": "Malachi", "full": "Malachi Napa", "last": "Napa"}, "stats": {"dateCoverageType": "event", "dateCoverageValue": "EFBO992369", "teamCoverage": "single-team", "timePlayedTotal": "4"}, "bookings": [], "substitutions": []}, "positionOfReplacement": "forward"}]}, {"meta": {"lineFormationPosition": "11", "playerKey": "PO96991", "positionRegular": "midfielder", "status": "starter", "uniformNumber": "11"}, "name": {"full": "Ryan Lloyd", "abbreviation": "Lloyd"}, "bookings": [], "substitutions": []}, {"meta": {"lineFormationPosition": "9", "playerKey": "PO138769", "positionRegular": "forward", "status": "starter", "uniformNumber": "9"}, "name": {"full": "Scott Wilson", "abbreviation": "Wilson"}, "bookings": [], "substitutions": []}, {"meta": {"lineFormationPosition": "0", "playerKey": "PO28586", "positionRegular": "defender", "status": "bench", "uniformNumber": "2"}, "name": {"full": "Jared Hodgkiss", "abbreviation": "Hodgkiss"}, "bookings": [], "substitutions": []}, {"meta": {"lineFormationPosition": "0", "playerKey": "PO18012", "positionRegular": "defender", "status": "bench", "uniformNumber": "4"}, "name": {"full": "Keith Lowe", "abbreviation": "Lowe"}, "bookings": [], "substitutions": []}, {"meta": {"lineFormationPosition": "0", "playerKey": "PO231805", "positionRegular": "defender", "status": "bench", "uniformNumber": "14"}, "name": {"full": "Miles Welch-Hayes", "abbreviation": "Welch-Hayes"}, "bookings": [], "substitutions": []}, {"meta": {"lineFormationPosition": "0", "playerKey": "PO432161", "positionRegular": "midfielder", "status": "bench", "uniformNumber": "16"}, "name": {"full": "Malachi Napa", "abbreviation": "Napa"}, "bookings": [], "substitutions": []}, {"meta": {"lineFormationPosition": "0", "playerKey": "PO47343", "positionRegular": "midfielder", "status": "bench", "uniformNumber": "20"}, "name": {"full": "Peter Vincenti", "abbreviation": "Vincenti"}, "bookings": [], "substitutions": []}, {"meta": {"lineFormationPosition": "0", "playerKey": "PO12195", "positionRegular": "midfielder", "status": "bench", "uniformNumber": "23"}, "name": {"full": "Danny Whitaker", "abbreviation": "Whitaker"}, "bookings": [], "substitutions": []}, {"meta": {"lineFormationPosition": "0", "playerKey": "PO215067", "positionRegular": "goalkeeper", "status": "bench", "uniformNumber": "28"}, "name": {"full": "Emmanuel Idem", "abbreviation": "Idem"}, "bookings": [], "substitutions": []}], "formation": 4231}, "awayTeam": {"name": "Tranmere Rovers", "nameAbbreviation": "Tranmere", "players": [{"meta": {"lineFormationPosition": "1", "playerKey": "PO40287", "positionRegular": "goalkeeper", "status": "starter", "uniformNumber": "1"}, "name": {"full": "Scott Davies", "abbreviation": "Davies"}, "bookings": [], "substitutions": []}, {"meta": {"lineFormationPosition": "2", "playerKey": "PO92806", "positionRegular": "defender", "status": "starter", "uniformNumber": "2"}, "name": {"full": "Adam Buxton", "abbreviation": "Buxton"}, "bookings": [], "substitutions": []}, {"meta": {"lineFormationPosition": "5", "playerKey": "PO48560", "positionRegular": "defender", "status": "starter", "uniformNumber": "16"}, "name": {"full": "Mark Ellis", "abbreviation": "Ellis"}, "bookings": [], "substitutions": []}, {"meta": {"lineFormationPosition": "6", "playerKey": "PO167889", "positionRegular": "defender", "status": "starter", "uniformNumber": "6"}, "name": {"full": "Emmanuel Monthe", "abbreviation": "Monthe"}, "bookings": [{"type": "yellow-card", "timeElapsed": 73, "addedTime": 0}], "substitutions": []}, {"meta": {"lineFormationPosition": "3", "playerKey": "PO67894", "positionRegular": "defender", "status": "starter", "uniformNumber": "3"}, "name": {"full": "Liam Ridehalgh", "abbreviation": "Ridehalgh"}, "bookings": [], "substitutions": []}, {"meta": {"lineFormationPosition": "7", "playerKey": "PO103102", "positionRegular": "midfielder", "status": "starter", "uniformNumber": "14"}, "name": {"full": "Jake Caprice", "abbreviation": "Caprice"}, "bookings": [], "substitutions": []}, {"meta": {"lineFormationPosition": "4", "playerKey": "PO152798", "positionRegular": "midfielder", "status": "starter", "uniformNumber": "12"}, "name": {"full": "Luke McCullough", "abbreviation": "McCullough"}, "bookings": [], "substitutions": []}, {"meta": {"lineFormationPosition": "8", "playerKey": "PO38426", "positionRegular": "midfielder", "status": "starter", "uniformNumber": "8"}, "name": {"full": "Jay Harris", "abbreviation": "Harris"}, "bookings": [], "substitutions": []}, {"meta": {"lineFormationPosition": "11", "playerKey": "PO223810", "positionRegular": "midfielder", "status": "starter", "uniformNumber": "18"}, "name": {"full": "Johnny Smith", "abbreviation": "Smith"}, "bookings": [], "substitutions": [{"type": "substitution", "timeElapsed": 69, "addedTime": 0, "reason": "Tactical", "replacedBy": {"meta": {"lineFormationPosition": "0", "playerKey": "PO106610", "positionRegular": "midfielder", "status": "bench", "uniformNumber": "29"}, "name": {"abbreviation": "Cole", "first": "Larnell", "full": "Larnell Cole", "last": "Cole"}, "stats": {"dateCoverageType": "event", "dateCoverageValue": "EFBO992369", "teamCoverage": "single-team", "timePlayedTotal": "21"}, "bookings": [], "substitutions": []}, "positionOfReplacement": "midfielder"}]}, {"meta": {"lineFormationPosition": "10", "playerKey": "PO71749", "positionRegular": "forward", "status": "starter", "uniformNumber": "10"}, "name": {"full": "James Norwood", "abbreviation": "Norwood"}, "bookings": [], "substitutions": []}, {"meta": {"lineFormationPosition": "9", "playerKey": "PO60295", "positionRegular": "forward", "status": "starter", "uniformNumber": "11"}, "name": {"full": "Connor Jennings", "abbreviation": "Jennings"}, "bookings": [{"type": "yellow-card", "timeElapsed": 75, "addedTime": 0}], "substitutions": []}, {"meta": {"lineFormationPosition": "0", "playerKey": "PO16066", "positionRegular": "defender", "status": "bench", "uniformNumber": "5"}, "name": {"full": "Steve McNulty", "abbreviation": "McNulty"}, "bookings": [], "substitutions": []}, {"meta": {"lineFormationPosition": "0", "playerKey": "PO167447", "positionRegular": "forward", "status": "bench", "uniformNumber": "9"}, "name": {"full": "Paul Mullin", "abbreviation": "Mullin"}, "bookings": [], "substitutions": []}, {"meta": {"lineFormationPosition": "0", "playerKey": "PO109674", "positionRegular": "forward", "status": "bench", "uniformNumber": "20"}, "name": {"full": "Cole Stockton", "abbreviation": "Stockton"}, "bookings": [], "substitutions": []}, {"meta": {"lineFormationPosition": "0", "playerKey": "PO225987", "positionRegular": "midfielder", "status": "bench", "uniformNumber": "22"}, "name": {"full": "Harvey Gilmour", "abbreviation": "Gilmour"}, "bookings": [], "substitutions": []}, {"meta": {"lineFormationPosition": "0", "playerKey": "PO170437", "positionRegular": "goalkeeper", "status": "bench", "uniformNumber": "23"}, "name": {"full": "Shamal George", "abbreviation": "George"}, "bookings": [], "substitutions": []}, {"meta": {"lineFormationPosition": "0", "playerKey": "PO39259", "positionRegular": "defender", "status": "bench", "uniformNumber": "24"}, "name": {"full": "Zoumana Bakayogo", "abbreviation": "Bakayogo"}, "bookings": [], "substitutions": []}, {"meta": {"lineFormationPosition": "0", "playerKey": "PO106610", "positionRegular": "midfielder", "status": "bench", "uniformNumber": "29"}, "name": {"full": "Larnell Cole", "abbreviation": "Cole"}, "bookings": [], "substitutions": []}], "formation": 442}}, "meta": {"referee": "Michael Salisbury", "attendance": "3,398"}}}